coordinate_comparison/__init__.py
coordinate_comparison/hand/__init__.py
coordinate_comparison/hand/yuxuan_similarity.py
coordinate_comparison/pose/__init__.py
coordinate_comparison/pose/yuxuan_similarity.py
coordinate_comparison/res/ContrastPoseRes.py
coordinate_comparison/utils/comparison_tools.py
coordinate_comparison-0.0.1.dist-info/METADATA
coordinate_comparison-0.0.1.dist-info/WHEEL
coordinate_comparison-0.0.1.dist-info/licenses/LICENSE
coordinate_comparison-0.0.1.dist-info/RECORD
